Metadata-Version: 2.1
Name: odoo-addon-barcodes_generator_location
Version: 17.0.1.0.1.1
Requires-Python: >=3.10
Requires-Dist: odoo-addon-barcodes_generator_abstract>=17.0dev,<17.1dev
Requires-Dist: odoo>=17.0a,<17.1dev
Summary: Generate Barcodes for Stock Locations
Home-page: https://github.com/OCA/stock-logistics-barcode
License: AGPL-3
Author: LasLabs, Odoo Community Association (OCA)
Author-email: support@odoo-community.org
Classifier: Programming Language :: Python
Classifier: Framework :: Odoo
Classifier: Framework :: Odoo :: 17.0
Classifier: License :: OSI Approved :: GNU Affero General Public License v3
